tspng/__init__.py
tspng/__main__.py
tspng/cli.py
tspng/extraction.py
tspng/implantation.py
tspng/test_extraction.py
tspng/test_implantation.py
tspng-1.1.0.dist-info/METADATA
tspng-1.1.0.dist-info/WHEEL
tspng-1.1.0.dist-info/entry_points.txt
tspng-1.1.0.dist-info/licenses/LICENSE
tspng-1.1.0.dist-info/RECORD
