Metadata-Version: 2.3
Name: tspng
Version: 1.1.0
Summary: A Python package for manipulating PNG files with embedded JSON related to Machine Learning.
Project-URL: Homepage, https://github.com/Theia-Scientific/tspng
Project-URL: Bug Tracker, https://github.com/Theia-Scientific/tspng/issues
Author-email: Theia Scientific <support@theiascientific.com>
License-File: LICENSE
Classifier: License :: OSI Approved :: MIT License
Classifier: Operating System :: OS Independent
Classifier: Programming Language :: Python :: 3
Requires-Python: >=3.9
Requires-Dist: pillow
Provides-Extra: cli
Requires-Dist: typer; extra == 'cli'
Provides-Extra: dev
Requires-Dist: build; extra == 'dev'
Requires-Dist: flake8; extra == 'dev'
Requires-Dist: pytest; extra == 'dev'
Requires-Dist: pytest-cov; extra == 'dev'
Requires-Dist: twine; extra == 'dev'
